vtktonumpy/__init__.py
vtktonumpy/vtkgrid.py
vtktonumpy/vtkreader.py
vtktonumpy-0.3.1.dist-info/LICENSE
vtktonumpy-0.3.1.dist-info/METADATA
vtktonumpy-0.3.1.dist-info/WHEEL
vtktonumpy-0.3.1.dist-info/top_level.txt
vtktonumpy-0.3.1.dist-info/RECORD
