Metadata-Version: 2.1
Name: vtktonumpy
Version: 0.3.1
Summary: Read VTK rectilinear grid files and output as N-dimensional NumPy arrays
Author: Declan B. Gaylo
License: MIT License
Project-URL: Homepage, https://github.com/dgaylo/VTKToNumpy
Project-URL: Bug Tracker, https://github.com/dgaylo/VTKToNumpy/issues
Project-URL: Documentation, https://dgaylo.github.io/VTKToNumpy
Classifier: Programming Language :: Python :: 3
Classifier: License :: OSI Approved :: MIT License
Requires-Python: >=3.6
License-File: LICENSE
Requires-Dist: numpy
Requires-Dist: vtk >=9.0
